[
  {
    "id": "1752480242282",
    "userId": "tho123",
    "userEmail": "thuan@gmail.com",
    "selectedGame": "QQ88",
    "gameUsername": "3412",
    "phoneLast4": "1231",
    "accountPoints": 50,
    "accountPrice": 30000,
    "accountWebsites": "F168 QQ88 78win OK9 MB66",
    "accountId": "8728b2336e852e17",
    "status": "rejected",
    "timestamp": 1752480242282,
    "createdAt": "2025-07-14T08:04:02.282Z",
    "balance": 99999,
    "adminNote": "Lý do không duyệt: Đơn lỗi hay tạo đơn khác"
  },
  {
    "id": "1752481103564",
    "userId": "tho123",
    "userEmail": "qkDVIm81Mko9woLzEPUzTw9C4nHcjHS+2qaCmqt4gHIgU0e0wXPCGsZ2XxY+oUX0waxU33witkm7uqnV07O6fA1SGs9/wAYPtQZKOgUlbePa7CV1nUfG6rWUzUMy0OtST3gkoy3T2UyTP8QHu7gO",
    "selectedGame": "78win",
    "gameUsername": "342342",
    "phoneLast4": "2134",
    "accountPoints": 50,
    "accountPrice": 30000,
    "accountWebsites": "F168 QQ88 78win OK9 MB66",
    "accountId": "effa1132dd36f4d3",
    "status": "rejected",
    "timestamp": 1752481103564,
    "createdAt": "2025-07-14T08:18:23.564Z",
    "balance": 99999,
    "adminNote": "Lý do không duyệt: Đơn lỗi hay tạo đơn khác"
  },
  {
    "id": "1752481399177",
    "userId": "tho123",
    "userEmail": "Tienthan@dd.dd",
    "selectedGame": "78win",
    "gameUsername": "312121212121212121212",
    "phoneLast4": "1212",
    "accountPoints": 530,
    "accountPrice": 270000,
    "accountWebsites": "F168 QQ88 78win OK9 MB66",
    "accountId": "71beee9ddc532d71",
    "status": "rejected",
    "timestamp": 1752481399177,
    "createdAt": "2025-07-14T08:23:19.177Z",
    "balance": 9999999,
    "adminNote": "Lý do không duyệt: Đơn lỗi hay tạo đơn khác"
  },
  {
    "id": "1752483299904",
    "userId": "tho123",
    "userEmail": "gTLZ4sRbHEEJOWht9bpLEgXyQXm2/4/MUiySIkigk1K1jxgn65aovIo4e0Wz/E2DJ1VJmxhpjI8o9RsnSKCYDSXS/FImsy0nVE/DLESydULHaGtQcmK1BtzM1DFKKqNJXoNpzSt26/7ofHJ8zeY=",
    "selectedGame": "QQ88",
    "gameUsername": "33333",
    "phoneLast4": "3333",
    "accountPoints": 530,
    "accountPrice": 270000,
    "accountWebsites": "F168 QQ88 78win OK9 MB66",
    "accountId": "76040f5d7b2831ac",
    "status": "rejected",
    "timestamp": 1752483299904,
    "createdAt": "2025-07-14T08:54:59.904Z",
    "balance": 9999999,
    "adminNote": "Lý do không duyệt: Đơn lỗi hay tạo đơn khác"
  },
  {
    "id": "1752483307165",
    "userId": "tho123",
    "userEmail": "gTLZ4sRbHEEJOWht9bpLEgXyQXm2/4/MUiySIkigk1K1jxgn65aovIo4e0Wz/E2DJ1VJmxhpjI8o9RsnSKCYDSXS/FImsy0nVE/DLESydULHaGtQcmK1BtzM1DFKKqNJXoNpzSt26/7ofHJ8zeY=",
    "selectedGame": "QQ88",
    "gameUsername": "33333333333",
    "phoneLast4": "3333",
    "accountPoints": 530,
    "accountPrice": 270000,
    "accountWebsites": "F168 QQ88 78win OK9 MB66",
    "accountId": "d17b424945741c04",
    "status": "rejected",
    "timestamp": 1752483307165,
    "createdAt": "2025-07-14T08:55:07.165Z",
    "balance": 9999999,
    "adminNote": "Lý do không duyệt: Đơn lỗi hay tạo đơn khác"
  },
  {
    "id": "1752483370210",
    "userId": "tho123",
    "userEmail": "gTLZ4sRbHEEJOWht9bpLEgXyQXm2/4/MUiySIkigk1K1jxgn65aovIo4e0Wz/E2DJ1VJmxhpjI8o9RsnSKCYDSXS/FImsy0nVE/DLESydULHaGtQcmK1BtzM1DFKKqNJXoNpzSt26/7ofHJ8zeY=",
    "selectedGame": "F168",
    "gameUsername": "wwwwww",
    "phoneLast4": "1231",
    "accountPoints": 503,
    "accountPrice": 257000,
    "accountWebsites": "F168 QQ88 78win OK9 MB66",
    "accountId": "eb595b5b10fc5847",
    "status": "completed",
    "timestamp": 1752483370210,
    "createdAt": "2025-07-14T08:56:10.210Z",
    "balance": 9999999,
    "adminNote": ""
  },
  {
    "id": "1752483789419",
    "userId": "tho123",
    "userEmail": "gTLZ4sRbHEEJOWht9bpLEgXyQXm2/4/MUiySIkigk1K1jxgn65aovIo4e0Wz/E2DJ1VJmxhpjI8o9RsnSKCYDSXS/FImsy0nVE/DLESydULHaGtQcmK1BtzM1DFKKqNJXoNpzSt26/7ofHJ8zeY=",
    "selectedGame": "QQ88",
    "gameUsername": "323213",
    "phoneLast4": "3232",
    "accountPoints": 250,
    "accountPrice": 130000,
    "accountWebsites": "F168 QQ88 78win OK9 MB66",
    "accountId": "08c1c83b83236ce2",
    "status": "pending",
    "timestamp": 1752483789419,
    "createdAt": "2025-07-14T09:03:09.419Z",
    "balance": 9999999
  }
]